jobdam/__init__.py
jobdam/api/auth_api.py
jobdam/api/chat_api.py
jobdam/config.json
jobdam/config.py
jobdam/constants.py
jobdam/ui/main.css
jobdam/ui/main.py
jobdam/ui/modals/error_modal.py
jobdam/ui/modals/leave_room_modal.py
jobdam/ui/modals/room_setting_modal.py
jobdam/ui/screens/chat_screen.py
jobdam/ui/screens/home_screen.py
jobdam/ui/screens/login_screen.py
jobdam/ui/screens/register_screen.py
jobdam/ui/screens/search_room_screen.py
jobdam/ui/widgets/chat_widget.py
jobdam/ui/widgets/home_widget.py
jobdam/ui/widgets/login_widget.py
jobdam/ui/widgets/register_widget.py
jobdam/ui/widgets/search_room_widget.py
jobdam/utils/auth_utils.py
jobdam/utils/global_utils.py
jobdam-0.1.9.dist-info/entry_points.txt
jobdam-0.1.9.dist-info/METADATA
jobdam-0.1.9.dist-info/WHEEL
jobdam-0.1.9.dist-info/RECORD
