Metadata-Version: 2.1
Name: jobdam
Version: 0.1.9
Summary: Release version 0.1.9
Author: Earthquakoo
Author-email: cream5343@gmail.com
Requires-Python: >=3.11,<4.0
Classifier: Programming Language :: Python :: 3
Classifier: Programming Language :: Python :: 3.11
Classifier: Programming Language :: Python :: 3.12
Requires-Dist: requests (>=2.31.0,<3.0.0)
Requires-Dist: textual-dev (>=1.2.1,<2.0.0)
Requires-Dist: websockets (>=12.0,<13.0)
